
<SceneText>
  <FriendlyName>Conversation_0267</FriendlyName>
  <Strings>
    <Section>Speaker</Section>
    <Entry>
      <PointerOffset>0xe0410</PointerOffset>
      <JapaneseText>兄妹の警戒心</JapaneseText>
      <EnglishText> </EnglishText>
      <Notes> </Notes>
      <Id>0</Id>
      <Status>To Do</Status>
    </Entry>
    <Entry>
      <PointerOffset>0xe041e</PointerOffset>
      <JapaneseText>教会裏の林</JapaneseText>
      <EnglishText> </EnglishText>
      <Notes> </Notes>
      <Id>1</Id>
      <Status>To Do</Status>
    </Entry>
    <Entry>
      <PointerOffset>0xe0429</PointerOffset>
      <JapaneseText>ふふ、いー感じ。</JapaneseText>
      <EnglishText> </EnglishText>
      <Notes> </Notes>
      <Id>2</Id>
      <Status>To Do</Status>
    </Entry>
    <Entry>
      <PointerOffset>0xe043a</PointerOffset>
      <JapaneseText>イライザ……？</JapaneseText>
      <EnglishText> </EnglishText>
      <Notes> </Notes>
      <Id>3</Id>
      <Status>To Do</Status>
    </Entry>
    <Entry>
      <PointerOffset>0xe0449</PointerOffset>
      <JapaneseText>ほら、クレス……。</JapaneseText>
      <EnglishText> </EnglishText>
      <Notes> </Notes>
      <Id>4</Id>
      <Status>To Do</Status>
    </Entry>
  </Strings>
  <Strings>
    <Section>system</Section>
  </Strings>
</SceneText>
