
<SceneText>
  <FriendlyName>Conversation_0403</FriendlyName>
  <Strings>
    <Section>Speaker</Section>
    <Entry>
      <PointerOffset>0x13a911</PointerOffset>
      <JapaneseText>クレスさんも……。</JapaneseText>
      <EnglishText> </EnglishText>
      <Notes> </Notes>
      <Id>0</Id>
      <Status>To Do</Status>
    </Entry>
    <Entry>
      <PointerOffset>0x13a924</PointerOffset>
      <JapaneseText>風邪……ひかないと……いい……な……。</JapaneseText>
      <EnglishText> </EnglishText>
      <Notes> </Notes>
      <Id>1</Id>
      <Status>To Do</Status>
    </Entry>
    <Entry>
      <PointerOffset>0x13a94b</PointerOffset>
      <JapaneseText>とっても……さむ……ぃ……。</JapaneseText>
      <EnglishText> </EnglishText>
      <Notes> </Notes>
      <Id>2</Id>
      <Status>To Do</Status>
    </Entry>
    <Entry>
      <PointerOffset>0x13a969</PointerOffset>
      <JapaneseText>アミィーっ！！</JapaneseText>
      <EnglishText> </EnglishText>
      <Notes> </Notes>
      <Id>3</Id>
      <Status>To Do</Status>
    </Entry>
  </Strings>
  <Strings>
    <Section>system</Section>
  </Strings>
</SceneText>
