
<SceneText>
  <FriendlyName>Conversation_0435</FriendlyName>
  <Strings>
    <Section>Speaker</Section>
    <Entry>
      <PointerOffset>0x15f9a8</PointerOffset>
      <JapaneseText>む、やるわね。</JapaneseText>
      <EnglishText> </EnglishText>
      <Notes> </Notes>
      <Id>0</Id>
      <Status>To Do</Status>
    </Entry>
    <Entry>
      <PointerOffset>0x15f9b7</PointerOffset>
      <JapaneseText>そんなわけないでしょうが</JapaneseText>
      <EnglishText> </EnglishText>
      <Notes> </Notes>
      <Id>1</Id>
      <Status>To Do</Status>
    </Entry>
    <Entry>
      <PointerOffset>0x15f9d0</PointerOffset>
      <JapaneseText>ぐっ……。</JapaneseText>
      <EnglishText> </EnglishText>
      <Notes> </Notes>
      <Id>2</Id>
      <Status>To Do</Status>
    </Entry>
    <Entry>
      <PointerOffset>0x15f9db</PointerOffset>
      <JapaneseText>リリスのガッツ</JapaneseText>
      <EnglishText> </EnglishText>
      <Notes> </Notes>
      <Id>3</Id>
      <Status>To Do</Status>
    </Entry>
    <Entry>
      <PointerOffset>0x15f9ed</PointerOffset>
      <JapaneseText>ビストロシャンバール</JapaneseText>
      <EnglishText> </EnglishText>
      <Notes> </Notes>
      <Id>4</Id>
      <Status>To Do</Status>
    </Entry>
    <Entry>
      <PointerOffset>0x15fa05</PointerOffset>
      <JapaneseText>はああ……。</JapaneseText>
      <EnglishText> </EnglishText>
      <Notes> </Notes>
      <Id>5</Id>
      <Status>To Do</Status>
    </Entry>
    <Entry>
      <PointerOffset>0x15fa12</PointerOffset>
      <JapaneseText>どうしました？</JapaneseText>
      <EnglishText> </EnglishText>
      <Notes> </Notes>
      <Id>6</Id>
      <Status>To Do</Status>
    </Entry>
    <Entry>
      <PointerOffset>0x15fa21</PointerOffset>
      <JapaneseText>味マスター１号。</JapaneseText>
      <EnglishText> </EnglishText>
      <Notes> </Notes>
      <Id>7</Id>
      <Status>To Do</Status>
    </Entry>
    <Entry>
      <PointerOffset>0x15fa32</PointerOffset>
      <JapaneseText>味マスター。</JapaneseText>
      <EnglishText> </EnglishText>
      <Notes> </Notes>
      <Id>8</Id>
      <Status>To Do</Status>
    </Entry>
    <Entry>
      <PointerOffset>0x15fa3f</PointerOffset>
      <JapaneseText>なんてうるわしいことばの響き。</JapaneseText>
      <EnglishText> </EnglishText>
      <Notes> </Notes>
      <Id>9</Id>
      <Status>To Do</Status>
    </Entry>
    <Entry>
      <PointerOffset>0x15fa5e</PointerOffset>
      <JapaneseText>でも、もうダメ。</JapaneseText>
      <EnglishText> </EnglishText>
      <Notes> </Notes>
      <Id>10</Id>
      <Status>To Do</Status>
    </Entry>
    <Entry>
      <PointerOffset>0x15fa6f</PointerOffset>
      <JapaneseText>その称号は、もはやあたしの物ではない。</JapaneseText>
      <EnglishText> </EnglishText>
      <Notes> </Notes>
      <Id>11</Id>
      <Status>To Do</Status>
    </Entry>
    <Entry>
      <PointerOffset>0x15fa96</PointerOffset>
      <JapaneseText>あの勝負のことなら、</JapaneseText>
      <EnglishText> </EnglishText>
      <Notes> </Notes>
      <Id>12</Id>
      <Status>To Do</Status>
    </Entry>
    <Entry>
      <PointerOffset>0x15faab</PointerOffset>
      <JapaneseText>お気になさる必要はありません。</JapaneseText>
      <EnglishText> </EnglishText>
      <Notes> </Notes>
      <Id>13</Id>
      <Status>To Do</Status>
    </Entry>
    <Entry>
      <PointerOffset>0x15faca</PointerOffset>
      <JapaneseText>自分はマスターが負けたなどと、</JapaneseText>
      <EnglishText> </EnglishText>
      <Notes> </Notes>
      <Id>14</Id>
      <Status>To Do</Status>
    </Entry>
    <Entry>
      <PointerOffset>0x15fae9</PointerOffset>
      <JapaneseText>これっぽっちも。あくまで……。</JapaneseText>
      <EnglishText> </EnglishText>
      <Notes> </Notes>
      <Id>15</Id>
      <Status>To Do</Status>
    </Entry>
    <Entry>
      <PointerOffset>0x15fb08</PointerOffset>
      <JapaneseText>裏づけのないなぐさめはよして。</JapaneseText>
      <EnglishText> </EnglishText>
      <Notes> </Notes>
      <Id>16</Id>
      <Status>To Do</Status>
    </Entry>
    <Entry>
      <PointerOffset>0x15fb27</PointerOffset>
      <JapaneseText>ますます自分が情けなくなる。</JapaneseText>
      <EnglishText> </EnglishText>
      <Notes> </Notes>
      <Id>17</Id>
      <Status>To Do</Status>
    </Entry>
    <Entry>
      <PointerOffset>0x15fb44</PointerOffset>
      <JapaneseText>マスター……。</JapaneseText>
      <EnglishText> </EnglishText>
      <Notes> </Notes>
      <Id>18</Id>
      <Status>To Do</Status>
    </Entry>
    <Entry>
      <PointerOffset>0x15fb53</PointerOffset>
      <JapaneseText>下がりなさい。</JapaneseText>
      <EnglishText> </EnglishText>
      <Notes> </Notes>
      <Id>19</Id>
      <Status>To Do</Status>
    </Entry>
    <Entry>
      <PointerOffset>0x15fb62</PointerOffset>
      <JapaneseText>今はひとりにしてほしいの。</JapaneseText>
      <EnglishText> </EnglishText>
      <Notes> </Notes>
      <Id>20</Id>
      <Status>To Do</Status>
    </Entry>
    <Entry>
      <PointerOffset>0x15fb80</PointerOffset>
      <JapaneseText>わからない。わからないわ。</JapaneseText>
      <EnglishText> </EnglishText>
      <Notes> </Notes>
      <Id>21</Id>
      <Status>To Do</Status>
    </Entry>
    <Entry>
      <PointerOffset>0x15fb9b</PointerOffset>
      <JapaneseText>あの味の秘密が、どうしても。</JapaneseText>
      <EnglishText> </EnglishText>
      <Notes> </Notes>
      <Id>22</Id>
      <Status>To Do</Status>
    </Entry>
    <Entry>
      <PointerOffset>0x15fbb8</PointerOffset>
      <JapaneseText>くっ……味マスターとなって３年。</JapaneseText>
      <EnglishText> </EnglishText>
      <Notes> </Notes>
      <Id>23</Id>
      <Status>To Do</Status>
    </Entry>
    <Entry>
      <PointerOffset>0x15fbd9</PointerOffset>
      <JapaneseText>料理界にこの人ありといわれたあたしが！</JapaneseText>
      <EnglishText> </EnglishText>
      <Notes> </Notes>
      <Id>24</Id>
      <Status>To Do</Status>
    </Entry>
    <Entry>
      <PointerOffset>0x15fc00</PointerOffset>
      <JapaneseText>あんな田舎者まるだしの、</JapaneseText>
      <EnglishText> </EnglishText>
      <Notes> </Notes>
      <Id>25</Id>
      <Status>To Do</Status>
    </Entry>
    <Entry>
      <PointerOffset>0x15fc19</PointerOffset>
      <JapaneseText>野蛮な娘に負けるだなんて。</JapaneseText>
      <EnglishText> </EnglishText>
      <Notes> </Notes>
      <Id>26</Id>
      <Status>To Do</Status>
    </Entry>
    <Entry>
      <PointerOffset>0x15fc3a</PointerOffset>
      <JapaneseText>ひええっ！</JapaneseText>
      <EnglishText> </EnglishText>
      <Notes> </Notes>
      <Id>27</Id>
      <Status>To Do</Status>
    </Entry>
    <Entry>
      <PointerOffset>0x15fc45</PointerOffset>
      <JapaneseText>いたたた……。</JapaneseText>
      <EnglishText> </EnglishText>
      <Notes> </Notes>
      <Id>28</Id>
      <Status>To Do</Status>
    </Entry>
    <Entry>
      <PointerOffset>0x15fc54</PointerOffset>
      <JapaneseText>こら、ディムロス。</JapaneseText>
      <EnglishText> </EnglishText>
      <Notes> </Notes>
      <Id>29</Id>
      <Status>To Do</Status>
    </Entry>
    <Entry>
      <PointerOffset>0x15fc67</PointerOffset>
      <JapaneseText>もう少しちゃんとやってよ。</JapaneseText>
      <EnglishText> </EnglishText>
      <Notes> </Notes>
      <Id>30</Id>
      <Status>To Do</Status>
    </Entry>
    <Entry>
      <PointerOffset>0x15fc82</PointerOffset>
      <JapaneseText>無茶いうな。</JapaneseText>
      <EnglishText> </EnglishText>
      <Notes> </Notes>
      <Id>31</Id>
      <Status>To Do</Status>
    </Entry>
    <Entry>
      <PointerOffset>0x15fc8f</PointerOffset>
      <JapaneseText>わたしだって、どこに出るかわからん。</JapaneseText>
      <EnglishText> </EnglishText>
      <Notes> </Notes>
      <Id>32</Id>
      <Status>To Do</Status>
    </Entry>
    <Entry>
      <PointerOffset>0x15fcb4</PointerOffset>
      <JapaneseText>とりあえず、空間移動には成功したのね？</JapaneseText>
      <EnglishText> </EnglishText>
      <Notes> </Notes>
      <Id>33</Id>
      <Status>To Do</Status>
    </Entry>
    <Entry>
      <PointerOffset>0x15fcdb</PointerOffset>
      <JapaneseText>そのはずだが、ここは……？</JapaneseText>
      <EnglishText> </EnglishText>
      <Notes> </Notes>
      <Id>34</Id>
      <Status>To Do</Status>
    </Entry>
    <Entry>
      <PointerOffset>0x15fcf6</PointerOffset>
      <JapaneseText>あっ、あなた！　どこから出てきたの？</JapaneseText>
      <EnglishText> </EnglishText>
      <Notes> </Notes>
      <Id>35</Id>
      <Status>To Do</Status>
    </Entry>
    <Entry>
      <PointerOffset>0x15fd1b</PointerOffset>
      <JapaneseText>それに、ひとりでブツブツしゃべって……。</JapaneseText>
      <EnglishText> </EnglishText>
      <Notes> </Notes>
      <Id>36</Id>
      <Status>To Do</Status>
    </Entry>
    <Entry>
      <PointerOffset>0x15fd44</PointerOffset>
      <JapaneseText>あ、あたしたち、怪しい者じゃないでーす。</JapaneseText>
      <EnglishText> </EnglishText>
      <Notes> </Notes>
      <Id>37</Id>
      <Status>To Do</Status>
    </Entry>
    <Entry>
      <PointerOffset>0x15fd6d</PointerOffset>
      <JapaneseText>思いっきり怪しいと思うが。</JapaneseText>
      <EnglishText> </EnglishText>
      <Notes> </Notes>
      <Id>38</Id>
      <Status>To Do</Status>
    </Entry>
    <Entry>
      <PointerOffset>0x15fd88</PointerOffset>
      <JapaneseText>あんたは黙ってなさいよ。</JapaneseText>
      <EnglishText> </EnglishText>
      <Notes> </Notes>
      <Id>39</Id>
      <Status>To Do</Status>
    </Entry>
    <Entry>
      <PointerOffset>0x15fda1</PointerOffset>
      <JapaneseText>あたし、たち？</JapaneseText>
      <EnglishText> </EnglishText>
      <Notes> </Notes>
      <Id>40</Id>
      <Status>To Do</Status>
    </Entry>
  </Strings>
  <Strings>
    <Section>system</Section>
  </Strings>
</SceneText>
