
<SceneText>
  <FriendlyName>Conversation_0620</FriendlyName>
  <Strings>
    <Section>Speaker</Section>
    <Entry>
      <PointerOffset>0x1ce509</PointerOffset>
      <JapaneseText>うーむ。</JapaneseText>
      <EnglishText> </EnglishText>
      <Notes> </Notes>
      <Id>0</Id>
      <Status>To Do</Status>
    </Entry>
    <Entry>
      <PointerOffset>0x1ce516</PointerOffset>
      <JapaneseText>…………。</JapaneseText>
      <EnglishText> </EnglishText>
      <Notes> </Notes>
      <Id>1</Id>
      <Status>To Do</Status>
    </Entry>
    <Entry>
      <PointerOffset>0x1ce525</PointerOffset>
      <JapaneseText>ダメだー！</JapaneseText>
      <EnglishText> </EnglishText>
      <Notes> </Notes>
      <Id>2</Id>
      <Status>To Do</Status>
    </Entry>
    <Entry>
      <PointerOffset>0x1ce530</PointerOffset>
      <JapaneseText>そもそも私考えるのは得意じゃない〜！</JapaneseText>
      <EnglishText> </EnglishText>
      <Notes> </Notes>
      <Id>3</Id>
      <Status>To Do</Status>
    </Entry>
    <Entry>
      <PointerOffset>0x1ce556</PointerOffset>
      <JapaneseText>うわーーー。</JapaneseText>
      <EnglishText> </EnglishText>
      <Notes> </Notes>
      <Id>4</Id>
      <Status>To Do</Status>
    </Entry>
    <Entry>
      <PointerOffset>0x1ce567</PointerOffset>
      <JapaneseText>うわーーー。</JapaneseText>
      <EnglishText> </EnglishText>
      <Notes> </Notes>
      <Id>5</Id>
      <Status>To Do</Status>
    </Entry>
    <Entry>
      <PointerOffset>0x1ce578</PointerOffset>
      <JapaneseText>……はあ。</JapaneseText>
      <EnglishText> </EnglishText>
      <Notes> </Notes>
      <Id>6</Id>
      <Status>To Do</Status>
    </Entry>
    <Entry>
      <PointerOffset>0x1ce587</PointerOffset>
      <JapaneseText>…………。</JapaneseText>
      <EnglishText> </EnglishText>
      <Notes> </Notes>
      <Id>7</Id>
      <Status>To Do</Status>
    </Entry>
    <Entry>
      <PointerOffset>0x1ce596</PointerOffset>
      <JapaneseText>でもさぁ……。</JapaneseText>
      <EnglishText> </EnglishText>
      <Notes> </Notes>
      <Id>8</Id>
      <Status>To Do</Status>
    </Entry>
    <Entry>
      <PointerOffset>0x1ce5a9</PointerOffset>
      <JapaneseText>私ひとりで事件を解決したら</JapaneseText>
      <EnglishText> </EnglishText>
      <Notes> </Notes>
      <Id>9</Id>
      <Status>To Do</Status>
    </Entry>
    <Entry>
      <PointerOffset>0x1ce5c5</PointerOffset>
      <JapaneseText>キール、きっと驚くだろうなぁ……</JapaneseText>
      <EnglishText> </EnglishText>
      <Notes> </Notes>
      <Id>10</Id>
      <Status>To Do</Status>
    </Entry>
    <Entry>
      <PointerOffset>0x1ce5e7</PointerOffset>
      <JapaneseText>えへへ……。</JapaneseText>
      <EnglishText> </EnglishText>
      <Notes> </Notes>
      <Id>11</Id>
      <Status>To Do</Status>
    </Entry>
    <Entry>
      <PointerOffset>0x1ce5fb</PointerOffset>
      <JapaneseText>ありがとう、プリムラ。</JapaneseText>
      <EnglishText> </EnglishText>
      <Notes> </Notes>
      <Id>12</Id>
      <Status>To Do</Status>
    </Entry>
    <Entry>
      <PointerOffset>0x1ce612</PointerOffset>
      <JapaneseText>君のおかげでこうして自由になれたよ。</JapaneseText>
      <EnglishText> </EnglishText>
      <Notes> </Notes>
      <Id>13</Id>
      <Status>To Do</Status>
    </Entry>
    <Entry>
      <PointerOffset>0x1ce638</PointerOffset>
      <JapaneseText>なんのなんの！</JapaneseText>
      <EnglishText> </EnglishText>
      <Notes> </Notes>
      <Id>14</Id>
      <Status>To Do</Status>
    </Entry>
    <Entry>
      <PointerOffset>0x1ce647</PointerOffset>
      <JapaneseText>私たち、パートナーじゃない！</JapaneseText>
      <EnglishText> </EnglishText>
      <Notes> </Notes>
      <Id>15</Id>
      <Status>To Do</Status>
    </Entry>
  </Strings>
  <Strings>
    <Section>system</Section>
  </Strings>
</SceneText>
