
<SceneText>
  <FriendlyName>Conversation_0678</FriendlyName>
  <Strings>
    <Section>Speaker</Section>
    <Entry>
      <PointerOffset>0x1f6a68</PointerOffset>
      <JapaneseText>名探偵ポイント</JapaneseText>
      <EnglishText> </EnglishText>
      <Notes> </Notes>
      <Id>0</Id>
      <Status>To Do</Status>
    </Entry>
    <Entry>
      <PointerOffset>0x1f6a77</PointerOffset>
      <JapaneseText>学生寮玄関</JapaneseText>
      <EnglishText> </EnglishText>
      <Notes> </Notes>
      <Id>1</Id>
      <Status>To Do</Status>
    </Entry>
    <Entry>
      <PointerOffset>0x1f6a82</PointerOffset>
      <JapaneseText>学生寮を出る場合は、</JapaneseText>
      <EnglishText> </EnglishText>
      <Notes> </Notes>
      <Id>2</Id>
      <Status>To Do</Status>
    </Entry>
    <Entry>
      <PointerOffset>0x1f6a97</PointerOffset>
      <JapaneseText>一階の玄関に行けばいいのね。</JapaneseText>
      <EnglishText> </EnglishText>
      <Notes> </Notes>
      <Id>3</Id>
      <Status>To Do</Status>
    </Entry>
    <Entry>
      <PointerOffset>0x1f6ab9</PointerOffset>
      <JapaneseText>一階に移動する</JapaneseText>
      <EnglishText> </EnglishText>
      <Notes> </Notes>
      <Id>4</Id>
      <Status>To Do</Status>
    </Entry>
    <Entry>
      <PointerOffset>0x1f6ac9</PointerOffset>
      <JapaneseText>二階に移動する</JapaneseText>
      <EnglishText> </EnglishText>
      <Notes> </Notes>
      <Id>5</Id>
      <Status>To Do</Status>
    </Entry>
    <Entry>
      <PointerOffset>0x1f6ad9</PointerOffset>
      <JapaneseText>三階に移動する</JapaneseText>
      <EnglishText> </EnglishText>
      <Notes> </Notes>
      <Id>6</Id>
      <Status>To Do</Status>
    </Entry>
    <Entry>
      <PointerOffset>0x1f6ae9</PointerOffset>
      <JapaneseText>四階に移動する</JapaneseText>
      <EnglishText> </EnglishText>
      <Notes> </Notes>
      <Id>7</Id>
      <Status>To Do</Status>
    </Entry>
    <Entry>
      <PointerOffset>0x1f6af9</PointerOffset>
      <JapaneseText>１０１　アン・ハイダウェイ</JapaneseText>
      <EnglishText> </EnglishText>
      <Notes> </Notes>
      <Id>8</Id>
      <Status>To Do</Status>
    </Entry>
    <Entry>
      <PointerOffset>0x1f6b17</PointerOffset>
      <JapaneseText>１０２　キーファ・パッカード</JapaneseText>
      <EnglishText> </EnglishText>
      <Notes> </Notes>
      <Id>9</Id>
      <Status>To Do</Status>
    </Entry>
  </Strings>
  <Strings>
    <Section>system</Section>
  </Strings>
</SceneText>
