
<SceneText>
  <FriendlyName>Conversation_0964</FriendlyName>
  <Strings>
    <Section>Speaker</Section>
    <Entry>
      <PointerOffset>0x29eb83</PointerOffset>
      <JapaneseText>ま、ま、食え、食え！</JapaneseText>
      <EnglishText> </EnglishText>
      <Notes> </Notes>
      <Id>0</Id>
      <Status>To Do</Status>
    </Entry>
    <Entry>
      <PointerOffset>0x29eb9b</PointerOffset>
      <JapaneseText>うめぇな、コレ。</JapaneseText>
      <EnglishText> </EnglishText>
      <Notes> </Notes>
      <Id>1</Id>
      <Status>To Do</Status>
    </Entry>
    <Entry>
      <PointerOffset>0x29ebaf</PointerOffset>
      <JapaneseText>だろ？　な？　最高だろ？</JapaneseText>
      <EnglishText> </EnglishText>
      <Notes> </Notes>
      <Id>2</Id>
      <Status>To Do</Status>
    </Entry>
    <Entry>
      <PointerOffset>0x29ebca</PointerOffset>
      <JapaneseText>ここは友好的ですね。</JapaneseText>
      <EnglishText> </EnglishText>
      <Notes> </Notes>
      <Id>3</Id>
      <Status>To Do</Status>
    </Entry>
    <Entry>
      <PointerOffset>0x29ebe2</PointerOffset>
      <JapaneseText>やっと落ち着けるかな……？</JapaneseText>
      <EnglishText> </EnglishText>
      <Notes> </Notes>
      <Id>4</Id>
      <Status>To Do</Status>
    </Entry>
    <Entry>
      <PointerOffset>0x29ebff</PointerOffset>
      <JapaneseText>なぁ、弓でする狩りって</JapaneseText>
      <EnglishText> </EnglishText>
      <Notes> </Notes>
      <Id>5</Id>
      <Status>To Do</Status>
    </Entry>
    <Entry>
      <PointerOffset>0x29ec16</PointerOffset>
      <JapaneseText>どんなモンなんだ？</JapaneseText>
      <EnglishText> </EnglishText>
      <Notes> </Notes>
      <Id>6</Id>
      <Status>To Do</Status>
    </Entry>
    <Entry>
      <PointerOffset>0x29ec2c</PointerOffset>
      <JapaneseText>弓はいいぜ。</JapaneseText>
      <EnglishText> </EnglishText>
      <Notes> </Notes>
      <Id>7</Id>
      <Status>To Do</Status>
    </Entry>
    <Entry>
      <PointerOffset>0x29ec3d</PointerOffset>
      <JapaneseText>狙いをすましてる時の静けさとか</JapaneseText>
      <EnglishText> </EnglishText>
      <Notes> </Notes>
      <Id>8</Id>
      <Status>To Do</Status>
    </Entry>
    <Entry>
      <PointerOffset>0x29ec5e</PointerOffset>
      <JapaneseText>風が耳元でうなる時の</JapaneseText>
      <EnglishText> </EnglishText>
      <Notes> </Notes>
      <Id>9</Id>
      <Status>To Do</Status>
    </Entry>
    <Entry>
      <PointerOffset>0x29ec73</PointerOffset>
      <JapaneseText>ぞくぞくした感じとか……。</JapaneseText>
      <EnglishText> </EnglishText>
      <Notes> </Notes>
      <Id>10</Id>
      <Status>To Do</Status>
    </Entry>
    <Entry>
      <PointerOffset>0x29ec8e</PointerOffset>
      <JapaneseText>うわ、いいなぁー！</JapaneseText>
      <EnglishText> </EnglishText>
      <Notes> </Notes>
      <Id>11</Id>
      <Status>To Do</Status>
    </Entry>
    <Entry>
      <PointerOffset>0x29eca1</PointerOffset>
      <JapaneseText>オレも使ってみてぇ！！</JapaneseText>
      <EnglishText> </EnglishText>
      <Notes> </Notes>
      <Id>12</Id>
      <Status>To Do</Status>
    </Entry>
    <Entry>
      <PointerOffset>0x29ecbb</PointerOffset>
      <JapaneseText>狩り以外にもいろいろ重宝してるんだ。</JapaneseText>
      <EnglishText> </EnglishText>
      <Notes> </Notes>
      <Id>13</Id>
      <Status>To Do</Status>
    </Entry>
    <Entry>
      <PointerOffset>0x29ece1</PointerOffset>
      <JapaneseText>たとえば……マイク代わりにするとか</JapaneseText>
      <EnglishText> </EnglishText>
      <Notes> </Notes>
      <Id>14</Id>
      <Status>To Do</Status>
    </Entry>
    <Entry>
      <PointerOffset>0x29ed05</PointerOffset>
      <JapaneseText>マイク？　おまえ、歌うのか？</JapaneseText>
      <EnglishText> </EnglishText>
      <Notes> </Notes>
      <Id>15</Id>
      <Status>To Do</Status>
    </Entry>
    <Entry>
      <PointerOffset>0x29ed24</PointerOffset>
      <JapaneseText>あぁ。気持ちいいぜ。</JapaneseText>
      <EnglishText> </EnglishText>
      <Notes> </Notes>
      <Id>16</Id>
      <Status>To Do</Status>
    </Entry>
    <Entry>
      <PointerOffset>0x29ed39</PointerOffset>
      <JapaneseText>狩りの帰り道とかに大声で……。</JapaneseText>
      <EnglishText> </EnglishText>
      <Notes> </Notes>
      <Id>17</Id>
      <Status>To Do</Status>
    </Entry>
    <Entry>
      <PointerOffset>0x29ed5a</PointerOffset>
      <JapaneseText>やな予感！</JapaneseText>
      <EnglishText> </EnglishText>
      <Notes> </Notes>
      <Id>18</Id>
      <Status>To Do</Status>
    </Entry>
    <Entry>
      <PointerOffset>0x29ed69</PointerOffset>
      <JapaneseText>オレもひとりだったら歌うぜ！</JapaneseText>
      <EnglishText> </EnglishText>
      <Notes> </Notes>
      <Id>19</Id>
      <Status>To Do</Status>
    </Entry>
    <Entry>
      <PointerOffset>0x29ed88</PointerOffset>
      <JapaneseText>いいよなぁ、歌は。</JapaneseText>
      <EnglishText> </EnglishText>
      <Notes> </Notes>
      <Id>20</Id>
      <Status>To Do</Status>
    </Entry>
    <Entry>
      <PointerOffset>0x29ed9b</PointerOffset>
      <JapaneseText>ラララッラ〜♪</JapaneseText>
      <EnglishText> </EnglishText>
      <Notes> </Notes>
      <Id>21</Id>
      <Status>To Do</Status>
    </Entry>
  </Strings>
  <Strings>
    <Section>system</Section>
  </Strings>
</SceneText>
