
<SceneText>
  <FriendlyName>Conversation_1039</FriendlyName>
  <Strings>
    <Section>Speaker</Section>
    <Entry>
      <PointerOffset>0x2d0e7b</PointerOffset>
      <JapaneseText>さーてと……。</JapaneseText>
      <EnglishText> </EnglishText>
      <Notes> </Notes>
      <Id>0</Id>
      <Status>To Do</Status>
    </Entry>
    <Entry>
      <PointerOffset>0x2d0e8a</PointerOffset>
      <JapaneseText>みつけたあっ！</JapaneseText>
      <EnglishText> </EnglishText>
      <Notes> </Notes>
      <Id>1</Id>
      <Status>To Do</Status>
    </Entry>
    <Entry>
      <PointerOffset>0x2d0e9b</PointerOffset>
      <JapaneseText>……って、なにこれ？</JapaneseText>
      <EnglishText> </EnglishText>
      <Notes> </Notes>
      <Id>2</Id>
      <Status>To Do</Status>
    </Entry>
    <Entry>
      <PointerOffset>0x2d0eb0</PointerOffset>
      <JapaneseText>単なるビンのフタじゃない！</JapaneseText>
      <EnglishText> </EnglishText>
      <Notes> </Notes>
      <Id>3</Id>
      <Status>To Do</Status>
    </Entry>
    <Entry>
      <PointerOffset>0x2d0ecb</PointerOffset>
      <JapaneseText>ああもう、まぎらわしい！</JapaneseText>
      <EnglishText> </EnglishText>
      <Notes> </Notes>
      <Id>4</Id>
      <Status>To Do</Status>
    </Entry>
    <Entry>
      <PointerOffset>0x2d0ee4</PointerOffset>
      <JapaneseText>こんなものは……！</JapaneseText>
      <EnglishText> </EnglishText>
      <Notes> </Notes>
      <Id>5</Id>
      <Status>To Do</Status>
    </Entry>
    <Entry>
      <PointerOffset>0x2d0ef8</PointerOffset>
      <JapaneseText>お待ちなさい、お嬢さん。</JapaneseText>
      <EnglishText> </EnglishText>
      <Notes> </Notes>
      <Id>6</Id>
      <Status>To Do</Status>
    </Entry>
  </Strings>
  <Strings>
    <Section>system</Section>
  </Strings>
</SceneText>
